{"sections":{"banner":{"type":"banner","disabled":true,"settings":{"image":"shopify:\/\/shop_images\/Cocktails_with_H-PROOF_5.png","image_darken":false,"subtitle":"","width":"wide","banner_height":"small","padding_top":0,"padding_bottom":0,"css_class":"","custom_css":""}},"main":{"type":"blog__main","blocks":{"00f32f78-a3e6-4b26-b09e-7cb25be57490":{"type":"recent_posts","settings":{"title":"Recent posts","blog":"","blog_post_count":10}}},"block_order":["00f32f78-a3e6-4b26-b09e-7cb25be57490"],"settings":{"blog_tags":false,"blog_posts_per_row":4,"blog_posts_per_page":50,"pagination_type":"basic_pagination","show_sidebar":false,"sidebar_position":"left","blog_author":false,"blog_date":false,"read_time":false,"blog_comment_count":false,"blog_show_tags":false,"blog_show_excerpt":true,"show_border":true,"button_label":"Get the recipe","button_type":"button--link-style","width":"standard","padding_top":41,"padding_bottom":0,"animation":"none","css_class":"","custom_css":""}}},"order":["banner","main"]}